taft/__init__.py
taft-1.0.1.dist-info/WHEEL
taft-1.0.1.dist-info/METADATA
taft-1.0.1.dist-info/DESCRIPTION.rst
taft-1.0.1.dist-info/top_level.txt
taft-1.0.1.dist-info/metadata.json
taft-1.0.1.dist-info/RECORD
