Metadata-Version: 2.0
Name: taft
Version: 1.0.1
Summary: Technical Analysis For Trading
Home-page: http://github.com/Savahi/taft
Author: Savahi
Author-email: sh@tradingene.ru
License: MIT
Keywords: technical analysis trading
Platform: UNKNOWN
Classifier: Development Status :: 3 - Alpha
Classifier: Intended Audience :: Developers
Requires-Dist: numpy
